allennlp_models/__init__.py
allennlp_models/pretrained.py
allennlp_models/version.py
allennlp_models/classification/__init__.py
allennlp_models/classification/dataset_readers/__init__.py
allennlp_models/classification/dataset_readers/boolq.py
allennlp_models/classification/dataset_readers/stanford_sentiment_tree_bank.py
allennlp_models/classification/models/__init__.py
allennlp_models/classification/models/biattentive_classification_network.py
allennlp_models/classification/models/transformer_classification_tt.py
allennlp_models/common/__init__.py
allennlp_models/common/ontonotes.py
allennlp_models/coref/__init__.py
allennlp_models/coref/util.py
allennlp_models/coref/dataset_readers/__init__.py
allennlp_models/coref/dataset_readers/conll.py
allennlp_models/coref/dataset_readers/preco.py
allennlp_models/coref/dataset_readers/winobias.py
allennlp_models/coref/metrics/__init__.py
allennlp_models/coref/metrics/conll_coref_scores.py
allennlp_models/coref/metrics/mention_recall.py
allennlp_models/coref/models/__init__.py
allennlp_models/coref/models/coref.py
allennlp_models/coref/predictors/__init__.py
allennlp_models/coref/predictors/coref.py
allennlp_models/generation/__init__.py
allennlp_models/generation/dataset_readers/__init__.py
allennlp_models/generation/dataset_readers/cnn_dm.py
allennlp_models/generation/dataset_readers/copynet_seq2seq.py
allennlp_models/generation/dataset_readers/seq2seq.py
allennlp_models/generation/models/__init__.py
allennlp_models/generation/models/bart.py
allennlp_models/generation/models/composed_seq2seq.py
allennlp_models/generation/models/copynet_seq2seq.py
allennlp_models/generation/models/simple_seq2seq.py
allennlp_models/generation/models/t5.py
allennlp_models/generation/modules/__init__.py
allennlp_models/generation/modules/decoder_nets/__init__.py
allennlp_models/generation/modules/decoder_nets/decoder_net.py
allennlp_models/generation/modules/decoder_nets/lstm_cell.py
allennlp_models-2.10.1.dist-info/LICENSE
allennlp_models-2.10.1.dist-info/METADATA
allennlp_models-2.10.1.dist-info/WHEEL
allennlp_models-2.10.1.dist-info/top_level.txt
allennlp_models-2.10.1.dist-info/RECORD
