Metadata-Version: 2.1
Name: allennlp_models
Version: 2.10.1
Summary: Officially supported models for the AllenNLP framework
Home-page: https://github.com/allenai/allennlp-models
Author: Allen Institute for Artificial Intelligence
Author-email: allennlp@allenai.org
License: Apache
Keywords: allennlp NLP deep learning machine reading semantic parsing parsers
Classifier: Intended Audience :: Science/Research
Classifier: Development Status :: 3 - Alpha
Classifier: License :: OSI Approved :: Apache Software License
Classifier: Programming Language :: Python :: 3
Classifier: Topic :: Scientific/Engineering :: Artificial Intelligence
Requires-Python: >=3.7.1
License-File: LICENSE
